safety_db/__init__.py
safety_db/insecure.json
safety_db/insecure_full.json
safety_db-2021.7.17.dist-info/LICENSE.txt
safety_db-2021.7.17.dist-info/METADATA
safety_db-2021.7.17.dist-info/WHEEL
safety_db-2021.7.17.dist-info/top_level.txt
safety_db-2021.7.17.dist-info/RECORD
