Metadata-Version: 2.1
Name: safety-db
Version: 2021.7.17
Summary: A curated database of insecure Python packages
Home-page: https://github.com/pyupio/safety-db/
Author: Jannis Gebauer
Author-email: support@pyup.io
License: Attribution-NonCommercial-ShareAlike 4.0 International
Keywords: security
Platform: UNKNOWN
Classifier: Programming Language :: Python :: 2.7
Classifier: Programming Language :: Python :: 3.4
Classifier: Programming Language :: Python :: 3.5
Classifier: Programming Language :: Python :: 3.6
Classifier: Environment :: Web Environment
Classifier: Intended Audience :: Developers
Classifier: Operating System :: OS Independent
Classifier: Development Status :: 5 - Production/Stable
License-File: LICENSE.txt
